inetnums
