Metadata-Version: 1.1
Name: inetnums
Version: 1.0.1
Summary: WHOIS inetnum tree builder
Home-page: https://github.com/mailru/inetnums
Author: Vadim Markovtsev
Author-email: gmarkhor@gmail.com
License: MIT
Download-URL: https://github.com/mailru/inetnums
Keywords: whois,inetnum
Platform: UNKNOWN
Classifier: Development Status :: 4 - Beta
Classifier: Environment :: Console
Classifier: Intended Audience :: Developers
Classifier: Intended Audience :: Telecommunications Industry
Classifier: License :: OSI Approved :: MIT License
Classifier: Operating System :: POSIX
Classifier: Programming Language :: Python :: 3.2
Classifier: Programming Language :: Python :: 3.3
Classifier: Programming Language :: Python :: 3.4
Classifier: Topic :: Internet
Classifier: Topic :: Scientific/Engineering
